xkd/__init__.py
xkd/xkd.py
xkd-0.1.8.dist-info/METADATA
xkd-0.1.8.dist-info/WHEEL
xkd-0.1.8.dist-info/top_level.txt
xkd-0.1.8.dist-info/RECORD
