Metadata-Version: 2.4
Name: xkd
Version: 0.1.8
Summary: 本模块用来帮助儿童进行3d编程学习，使用简化的语法让孩子们更容易得学习编程，促进孩子们对于三维数学和三维编程的理解和使用。
Author-email: Jiabao Yang <airfly000@163.com>
Classifier: Programming Language :: Python :: 3
Classifier: License :: OSI Approved :: MIT License
Classifier: Operating System :: OS Independent
Requires-Python: >=3.7
Requires-Dist: panda3d>=1.10.15
Requires-Dist: panda3d-gltf>=1.2.0
